odoo8_addon_business_requirement_deliverable_project_task_categ-8.0.1.0.2-py2.7-nspkg.pth
odoo8_addon_business_requirement_deliverable_project_task_categ-8.0.1.0.2.dist-info/DESCRIPTION.rst
odoo8_addon_business_requirement_deliverable_project_task_categ-8.0.1.0.2.dist-info/METADATA
odoo8_addon_business_requirement_deliverable_project_task_categ-8.0.1.0.2.dist-info/RECORD
odoo8_addon_business_requirement_deliverable_project_task_categ-8.0.1.0.2.dist-info/WHEEL
odoo8_addon_business_requirement_deliverable_project_task_categ-8.0.1.0.2.dist-info/metadata.json
odoo8_addon_business_requirement_deliverable_project_task_categ-8.0.1.0.2.dist-info/namespace_packages.txt
odoo8_addon_business_requirement_deliverable_project_task_categ-8.0.1.0.2.dist-info/top_level.txt
odoo_addons/business_requirement_deliverable_project_task_categ/README.rst
odoo_addons/business_requirement_deliverable_project_task_categ/__init__.py
odoo_addons/business_requirement_deliverable_project_task_categ/__openerp__.py
odoo_addons/business_requirement_deliverable_project_task_categ/i18n/sl.po
odoo_addons/business_requirement_deliverable_project_task_categ/models/__init__.py
odoo_addons/business_requirement_deliverable_project_task_categ/models/business_requirement_resource.py
odoo_addons/business_requirement_deliverable_project_task_categ/static/description/icon.png
odoo_addons/business_requirement_deliverable_project_task_categ/static/img/bus_req_category.png
odoo_addons/business_requirement_deliverable_project_task_categ/views/business_requirement_deliverable.xml
odoo_addons/business_requirement_deliverable_project_task_categ/wizard/__init__.py
odoo_addons/business_requirement_deliverable_project_task_categ/wizard/generate_projects.py
